[
  {
    "skillId": 1100,
    "imageId": 0,
    "thumbId": 1,
    "name": "Attack Boost I",
    "description": "Deals 1.2 times more damage.",
    "rank": 1,
    "maxLv": 10,
    "expType": 1,
    "sortId": 1100,
    "categoryEvolve": 1,
    "invokeType": 1,
    "invokeProb": 4000,
    "invokeProbPerLv": 80,
    "invokeShowTiming": 1,
    "attackUp": 12000,
    "burstCancel": 0,
    "damageCut": 0,
    "dokonjo": 10000,
    "counter": 0,
    "addAction": 0,
    "addPoison": 0,
    "addDeepPoison": 0,
    "addSleep": 0,
    "addParalysis": 0,
    "conditionTurn": 0,
    "conditionCount": 0,
    "prizeHpUp": 0,
    "prizeBurstUp": 10000,
    "luxUp": 10000,
    "moneyUp": 10000,
    "raidUp": 10000
  },
  {
    "skillId": 1101,
    "imageId": 0,
    "thumbId": 1,
    "name": "Attack Boost II",
    "description": "Deals 1.4 times more damage.",
    "rank": 2,
    "maxLv": 15,
    "expType": 2,
    "sortId": 1101,
    "categoryEvolve": 2,
    "invokeType": 1,
    "invokeProb": 4000,
    "invokeProbPerLv": 80,
    "invokeShowTiming": 1,
    "attackUp": 14000,
    "burstCancel": 0,
    "damageCut": 0,
    "dokonjo": 10000,
    "counter": 0,
    "addAction": 0,
    "addPoison": 0,
    "addDeepPoison": 0,
    "addSleep": 0,
    "addParalysis": 0,
    "conditionTurn": 0,
    "conditionCount": 0,
    "prizeHpUp": 0,
    "prizeBurstUp": 10000,
    "luxUp": 10000,
    "moneyUp": 10000,
    "raidUp": 10000
  },
  {
    "skillId": 1102,
    "imageId": 0,
    "thumbId": 1,
    "name": "Attack Boost All I",
    "description": "Deals 1.2 times more damage when attacking all enemies.",
    "rank": 1,
    "maxLv": 10,
    "expType": 1,
    "sortId": 1102,
    "categoryEvolve": 3,
    "invokeType": 5,
    "invokeProb": 6000,
    "invokeProbPerLv": 80,
    "invokeShowTiming": 1,
    "attackUp": 12000,
    "burstCancel": 0,
    "damageCut": 0,
    "dokonjo": 10000,
    "counter": 0,
    "addAction": 0,
    "addPoison": 0,
    "addDeepPoison": 0,
    "addSleep": 0,
    "addParalysis": 0,
    "conditionTurn": 0,
    "conditionCount": 0,
    "prizeHpUp": 0,
    "prizeBurstUp": 10000,
    "luxUp": 10000,
    "moneyUp": 10000,
    "raidUp": 10000
  },
  {
    "skillId": 1103,
    "imageId": 0,
    "thumbId": 1,
    "name": "Attack Boost All II",
    "description": "Deals 1.4 times more damage when attacking all enemies.",
    "rank": 2,
    "maxLv": 15,
    "expType": 2,
    "sortId": 1103,
    "categoryEvolve": 4,
    "invokeType": 5,
    "invokeProb": 6000,
    "invokeProbPerLv": 80,
    "invokeShowTiming": 1,
    "attackUp": 14000,
    "burstCancel": 0,
    "damageCut": 0,
    "dokonjo": 10000,
    "counter": 0,
    "addAction": 0,
    "addPoison": 0,
    "addDeepPoison": 0,
    "addSleep": 0,
    "addParalysis": 0,
    "conditionTurn": 0,
    "conditionCount": 0,
    "prizeHpUp": 0,
    "prizeBurstUp": 10000,
    "luxUp": 10000,
    "moneyUp": 10000,
    "raidUp": 10000
  },
  {
    "skillId": 1104,
    "imageId": 0,
    "thumbId": 4,
    "name": "Poison",
    "description": "Poisons the enemy.",
    "rank": 1,
    "maxLv": 10,
    "expType": 1,
    "sortId": 1104,
    "categoryEvolve": 5,
    "invokeType": 7,
    "invokeProb": 3500,
    "invokeProbPerLv": 100,
    "invokeShowTiming": 1,
    "attackUp": 10000,
    "burstCancel": 0,
    "damageCut": 0,
    "dokonjo": 10000,
    "counter": 0,
    "addAction": 0,
    "addPoison": 0,
    "addDeepPoison": 10000,
    "addSleep": 0,
    "addParalysis": 0,
    "conditionTurn": 0,
    "conditionCount": 2,
    "prizeHpUp": 0,
    "prizeBurstUp": 10000,
    "luxUp": 10000,
    "moneyUp": 10000,
    "raidUp": 10000
  },
  {
    "skillId": 1105,
    "imageId": 0,
    "thumbId": 4,
    "name": "Paralysis",
    "description": "Paralyzes the enemy.",
    "rank": 1,
    "maxLv": 10,
    "expType": 1,
    "sortId": 1105,
    "categoryEvolve": 6,
    "invokeType": 7,
    "invokeProb": 3500,
    "invokeProbPerLv": 100,
    "invokeShowTiming": 1,
    "attackUp": 10000,
    "burstCancel": 0,
    "damageCut": 0,
    "dokonjo": 10000,
    "counter": 0,
    "addAction": 0,
    "addPoison": 0,
    "addDeepPoison": 0,
    "addSleep": 0,
    "addParalysis": 0,
    "conditionTurn": 10000,
    "conditionCount": 2,
    "prizeHpUp": 0,
    "prizeBurstUp": 10000,
    "luxUp": 10000,
    "moneyUp": 10000,
    "raidUp": 10000
  },
  {
    "skillId": 1106,
    "imageId": 0,
    "thumbId": 4,
    "name": "Sleep",
    "description": "Puts the enemy to sleep.",
    "rank": 1,
    "maxLv": 10,
    "expType": 1,
    "sortId": 1106,
    "categoryEvolve": 7,
    "invokeType": 7,
    "invokeProb": 3500,
    "invokeProbPerLv": 100,
    "invokeShowTiming": 1,
    "attackUp": 10000,
    "burstCancel": 0,
    "damageCut": 0,
    "dokonjo": 10000,
    "counter": 0,
    "addAction": 0,
    "addPoison": 0,
    "addDeepPoison": 0,
    "addSleep": 0,
    "addParalysis": 10000,
    "conditionTurn": 0,
    "conditionCount": 2,
    "prizeHpUp": 0,
    "prizeBurstUp": 10000,
    "luxUp": 10000,
    "moneyUp": 10000,
    "raidUp": 10000
  },
  {
    "skillId": 1107,
    "imageId": 0,
    "thumbId": 3,
    "name": "Attack Prize Plus",
    "description": "Increases attack prizes dropped by enemies.",
    "rank": 2,
    "maxLv": 15,
    "expType": 2,
    "sortId": 1107,
    "categoryEvolve": 8,
    "invokeType": 1,
    "invokeProb": 3500,
    "invokeProbPerLv": 50,
    "invokeShowTiming": 1,
    "attackUp": 10000,
    "burstCancel": 0,
    "damageCut": 0,
    "dokonjo": 10000,
    "counter": 0,
    "addAction": 0,
    "addPoison": 0,
    "addDeepPoison": 0,
    "addSleep": 0,
    "addParalysis": 0,
    "conditionTurn": 0,
    "conditionCount": 0,
    "prizeHpUp": 0,
    "prizeBurstUp": 10000,
    "luxUp": 220000,
    "moneyUp": 10000,
    "raidUp": 10000
  },
  {
    "skillId": 1109,
    "imageId": 0,
    "thumbId": 3,
    "name": "Lux Plus",
    "description": "Increases Lux dropped by enemies.",
    "rank": 2,
    "maxLv": 15,
    "expType": 2,
    "sortId": 1109,
    "categoryEvolve": 10,
    "invokeType": 1,
    "invokeProb": 3500,
    "invokeProbPerLv": 50,
    "invokeShowTiming": 1,
    "attackUp": 10000,
    "burstCancel": 0,
    "damageCut": 0,
    "dokonjo": 10000,
    "counter": 0,
    "addAction": 0,
    "addPoison": 0,
    "addDeepPoison": 0,
    "addSleep": 0,
    "addParalysis": 0,
    "conditionTurn": 0,
    "conditionCount": 0,
    "prizeHpUp": 0,
    "prizeBurstUp": 10000,
    "luxUp": 10000,
    "moneyUp": 30000,
    "raidUp": 10000
  },
  {
    "skillId": 1110,
    "imageId": 0,
    "thumbId": 5,
    "name": "No Cost",
    "description": "Triggers a special attack for free.",
    "rank": 3,
    "maxLv": 20,
    "expType": 3,
    "sortId": 1110,
    "categoryEvolve": 11,
    "invokeType": 4,
    "invokeProb": 4000,
    "invokeProbPerLv": 50,
    "invokeShowTiming": 5,
    "attackUp": 10000,
    "burstCancel": 1,
    "damageCut": 0,
    "dokonjo": 10000,
    "counter": 0,
    "addAction": 0,
    "addPoison": 0,
    "addDeepPoison": 0,
    "addSleep": 0,
    "addParalysis": 0,
    "conditionTurn": 0,
    "conditionCount": 0,
    "prizeHpUp": 0,
    "prizeBurstUp": 10000,
    "luxUp": 10000,
    "moneyUp": 10000,
    "raidUp": 10000
  },
  {
    "skillId": 1112,
    "imageId": 0,
    "thumbId": 2,
    "name": "Defense Boost I",
    "description": "Cuts enemy damage by 1/2.",
    "rank": 1,
    "maxLv": 10,
    "expType": 1,
    "sortId": 1112,
    "categoryEvolve": 13,
    "invokeType": 2,
    "invokeProb": 3000,
    "invokeProbPerLv": 50,
    "invokeShowTiming": 2,
    "attackUp": 10000,
    "burstCancel": 0,
    "damageCut": 0,
    "dokonjo": 5000,
    "counter": 0,
    "addAction": 0,
    "addPoison": 0,
    "addDeepPoison": 0,
    "addSleep": 0,
    "addParalysis": 0,
    "conditionTurn": 0,
    "conditionCount": 0,
    "prizeHpUp": 0,
    "prizeBurstUp": 10000,
    "luxUp": 10000,
    "moneyUp": 10000,
    "raidUp": 10000
  },
  {
    "skillId": 1113,
    "imageId": 0,
    "thumbId": 2,
    "name": "Defense Boost II",
    "description": "Cuts enemy damage by 2/3.",
    "rank": 2,
    "maxLv": 15,
    "expType": 2,
    "sortId": 1113,
    "categoryEvolve": 14,
    "invokeType": 2,
    "invokeProb": 3000,
    "invokeProbPerLv": 50,
    "invokeShowTiming": 2,
    "attackUp": 10000,
    "burstCancel": 0,
    "damageCut": 0,
    "dokonjo": 3333,
    "counter": 0,
    "addAction": 0,
    "addPoison": 0,
    "addDeepPoison": 0,
    "addSleep": 0,
    "addParalysis": 0,
    "conditionTurn": 0,
    "conditionCount": 0,
    "prizeHpUp": 0,
    "prizeBurstUp": 10000,
    "luxUp": 10000,
    "moneyUp": 10000,
    "raidUp": 10000
  },
  {
    "skillId": 1114,
    "imageId": 0,
    "thumbId": 3,
    "name": "ATK Boost II & Lux Plus",
    "description": "Deals 1.4 times more damage, and greatly increases Lux dropped by enemies.",
    "rank": 3,
    "maxLv": 20,
    "expType": 3,
    "sortId": 1114,
    "categoryEvolve": 21,
    "invokeType": 1,
    "invokeProb": 4000,
    "invokeProbPerLv": 60,
    "invokeShowTiming": 1,
    "attackUp": 14000,
    "burstCancel": 0,
    "damageCut": 0,
    "dokonjo": 10000,
    "counter": 0,
    "addAction": 0,
    "addPoison": 0,
    "addDeepPoison": 0,
    "addSleep": 0,
    "addParalysis": 0,
    "conditionTurn": 0,
    "conditionCount": 0,
    "prizeHpUp": 0,
    "prizeBurstUp": 10000,
    "luxUp": 10000,
    "moneyUp": 30000,
    "raidUp": 10000
  },
  {
    "skillId": 1115,
    "imageId": 0,
    "thumbId": 1,
    "name": "Attack Boost III",
    "description": "Deals 1.6 times more damage.",
    "rank": 3,
    "maxLv": 20,
    "expType": 3,
    "sortId": 1115,
    "categoryEvolve": 19,
    "invokeType": 1,
    "invokeProb": 4000,
    "invokeProbPerLv": 75,
    "invokeShowTiming": 1,
    "attackUp": 16000,
    "burstCancel": 0,
    "damageCut": 0,
    "dokonjo": 10000,
    "counter": 0,
    "addAction": 0,
    "addPoison": 0,
    "addDeepPoison": 0,
    "addSleep": 0,
    "addParalysis": 0,
    "conditionTurn": 0,
    "conditionCount": 0,
    "prizeHpUp": 0,
    "prizeBurstUp": 10000,
    "luxUp": 10000,
    "moneyUp": 10000,
    "raidUp": 10000
  },
  {
    "skillId": 1116,
    "imageId": 0,
    "thumbId": 5,
    "name": "Second Chance",
    "description": "With 2 or more HP, leaves 1 HP when hit with a fatal blow.",
    "rank": 2,
    "maxLv": 15,
    "expType": 2,
    "sortId": 1116,
    "categoryEvolve": 17,
    "invokeType": 3,
    "invokeProb": 2500,
    "invokeProbPerLv": 50,
    "invokeShowTiming": 4,
    "attackUp": 10000,
    "burstCancel": 0,
    "damageCut": 0,
    "dokonjo": 10000,
    "counter": 1,
    "addAction": 0,
    "addPoison": 0,
    "addDeepPoison": 0,
    "addSleep": 0,
    "addParalysis": 0,
    "conditionTurn": 0,
    "conditionCount": 0,
    "prizeHpUp": 0,
    "prizeBurstUp": 10000,
    "luxUp": 10000,
    "moneyUp": 10000,
    "raidUp": 10000
  },
  {
    "skillId": 1117,
    "imageId": 0,
    "thumbId": 3,
    "name": "ATK Prize+ & ATK Boost II",
    "description": "Deals 1.4 times more damage, and greatly increases attack prizes dropped by enemies.",
    "rank": 3,
    "maxLv": 20,
    "expType": 3,
    "sortId": 1117,
    "categoryEvolve": 22,
    "invokeType": 1,
    "invokeProb": 3500,
    "invokeProbPerLv": 50,
    "invokeShowTiming": 1,
    "attackUp": 14000,
    "burstCancel": 0,
    "damageCut": 0,
    "dokonjo": 10000,
    "counter": 0,
    "addAction": 0,
    "addPoison": 0,
    "addDeepPoison": 0,
    "addSleep": 0,
    "addParalysis": 0,
    "conditionTurn": 0,
    "conditionCount": 0,
    "prizeHpUp": 0,
    "prizeBurstUp": 10000,
    "luxUp": 220000,
    "moneyUp": 10000,
    "raidUp": 10000
  },
  {
    "skillId": 1118,
    "imageId": 0,
    "thumbId": 1,
    "name": "Attack Boost II Max",
    "description": "Deals 1.4 times more damage. Has a 100% trigger rate at max level.",
    "rank": 3,
    "maxLv": 20,
    "expType": 3,
    "sortId": 1118,
    "categoryEvolve": 23,
    "invokeType": 1,
    "invokeProb": 9810,
    "invokeProbPerLv": 10,
    "invokeShowTiming": 1,
    "attackUp": 14000,
    "burstCancel": 0,
    "damageCut": 0,
    "dokonjo": 10000,
    "counter": 0,
    "addAction": 0,
    "addPoison": 0,
    "addDeepPoison": 0,
    "addSleep": 0,
    "addParalysis": 0,
    "conditionTurn": 0,
    "conditionCount": 0,
    "prizeHpUp": 0,
    "prizeBurstUp": 10000,
    "luxUp": 10000,
    "moneyUp": 10000,
    "raidUp": 10000
  },
  {
    "skillId": 1119,
    "imageId": 0,
    "thumbId": 2,
    "name": "Defense Boost III",
    "description": "Negates enemy damage by 80%.",
    "rank": 3,
    "maxLv": 20,
    "expType": 3,
    "sortId": 1119,
    "categoryEvolve": 20,
    "invokeType": 2,
    "invokeProb": 3000,
    "invokeProbPerLv": 50,
    "invokeShowTiming": 2,
    "attackUp": 10000,
    "burstCancel": 0,
    "damageCut": 0,
    "dokonjo": 2000,
    "counter": 0,
    "addAction": 0,
    "addPoison": 0,
    "addDeepPoison": 0,
    "addSleep": 0,
    "addParalysis": 0,
    "conditionTurn": 0,
    "conditionCount": 0,
    "prizeHpUp": 0,
    "prizeBurstUp": 10000,
    "luxUp": 10000,
    "moneyUp": 10000,
    "raidUp": 10000
  },
  {
    "skillId": 1120,
    "imageId": 0,
    "thumbId": 4,
    "name": "Poison+",
    "description": "Casts Poison with single, group, or special attacks. Has a shorter duration than the original skill.",
    "rank": 2,
    "maxLv": 15,
    "expType": 2,
    "sortId": 1120,
    "categoryEvolve": 25,
    "invokeType": 1,
    "invokeProb": 4000,
    "invokeProbPerLv": 100,
    "invokeShowTiming": 1,
    "attackUp": 10000,
    "burstCancel": 0,
    "damageCut": 0,
    "dokonjo": 10000,
    "counter": 0,
    "addAction": 0,
    "addPoison": 0,
    "addDeepPoison": 10000,
    "addSleep": 0,
    "addParalysis": 0,
    "conditionTurn": 0,
    "conditionCount": 1,
    "prizeHpUp": 0,
    "prizeBurstUp": 10000,
    "luxUp": 10000,
    "moneyUp": 10000,
    "raidUp": 10000
  },
  {
    "skillId": 1121,
    "imageId": 0,
    "thumbId": 4,
    "name": "Paralysis+",
    "description": "Casts Paralysis with single, group, or special attacks. Has a shorter duration than the original skill.",
    "rank": 2,
    "maxLv": 15,
    "expType": 2,
    "sortId": 1121,
    "categoryEvolve": 26,
    "invokeType": 1,
    "invokeProb": 4000,
    "invokeProbPerLv": 100,
    "invokeShowTiming": 1,
    "attackUp": 10000,
    "burstCancel": 0,
    "damageCut": 0,
    "dokonjo": 10000,
    "counter": 0,
    "addAction": 0,
    "addPoison": 0,
    "addDeepPoison": 0,
    "addSleep": 0,
    "addParalysis": 0,
    "conditionTurn": 10000,
    "conditionCount": 1,
    "prizeHpUp": 0,
    "prizeBurstUp": 10000,
    "luxUp": 10000,
    "moneyUp": 10000,
    "raidUp": 10000
  },
  {
    "skillId": 1122,
    "imageId": 0,
    "thumbId": 4,
    "name": "Sleep+",
    "description": "Casts Sleep with single, group, or special attacks. Has a shorter duration than the original skill.",
    "rank": 2,
    "maxLv": 15,
    "expType": 2,
    "sortId": 1122,
    "categoryEvolve": 27,
    "invokeType": 1,
    "invokeProb": 4000,
    "invokeProbPerLv": 100,
    "invokeShowTiming": 1,
    "attackUp": 10000,
    "burstCancel": 0,
    "damageCut": 0,
    "dokonjo": 10000,
    "counter": 0,
    "addAction": 0,
    "addPoison": 0,
    "addDeepPoison": 0,
    "addSleep": 0,
    "addParalysis": 10000,
    "conditionTurn": 0,
    "conditionCount": 1,
    "prizeHpUp": 0,
    "prizeBurstUp": 10000,
    "luxUp": 10000,
    "moneyUp": 10000,
    "raidUp": 10000
  },
  {
    "skillId": 1123,
    "imageId": 0,
    "thumbId": 3,
    "name": "ATK Boost III & Lux Plus",
    "description": "Deals 1.6 times more damage, and greatly increases Lux dropped by enemies.",
    "rank": 3,
    "maxLv": 20,
    "expType": 3,
    "sortId": 1123,
    "categoryEvolve": 28,
    "invokeType": 1,
    "invokeProb": 4000,
    "invokeProbPerLv": 75,
    "invokeShowTiming": 1,
    "attackUp": 16000,
    "burstCancel": 0,
    "damageCut": 0,
    "dokonjo": 10000,
    "counter": 0,
    "addAction": 0,
    "addPoison": 0,
    "addDeepPoison": 0,
    "addSleep": 0,
    "addParalysis": 0,
    "conditionTurn": 0,
    "conditionCount": 0,
    "prizeHpUp": 0,
    "prizeBurstUp": 10000,
    "luxUp": 10000,
    "moneyUp": 30000,
    "raidUp": 10000
  },
  {
    "skillId": 1124,
    "imageId": 0,
    "thumbId": 5,
    "name": "SP Attack Gauge I",
    "description": "Uses only 1 special attack gauge. Has a 100% trigger rate.",
    "rank": 3,
    "maxLv": 20,
    "expType": 3,
    "sortId": 1124,
    "categoryEvolve": 29,
    "invokeType": 4,
    "invokeProb": 10000,
    "invokeProbPerLv": 0,
    "invokeShowTiming": 5,
    "attackUp": 10000,
    "burstCancel": 0,
    "damageCut": 10000,
    "dokonjo": 10000,
    "counter": 0,
    "addAction": 0,
    "addPoison": 0,
    "addDeepPoison": 0,
    "addSleep": 0,
    "addParalysis": 0,
    "conditionTurn": 0,
    "conditionCount": 0,
    "prizeHpUp": 0,
    "prizeBurstUp": 10000,
    "luxUp": 10000,
    "moneyUp": 10000,
    "raidUp": 10000
  },
  {
    "skillId": 1125,
    "imageId": 0,
    "thumbId": 1,
    "name": "Attack Boost III Max",
    "description": "Deals 1.6 times more damage. Has a 100% trigger rate at max level.",
    "rank": 3,
    "maxLv": 20,
    "expType": 3,
    "sortId": 1125,
    "categoryEvolve": 30,
    "invokeType": 1,
    "invokeProb": 9810,
    "invokeProbPerLv": 10,
    "invokeShowTiming": 1,
    "attackUp": 16000,
    "burstCancel": 0,
    "damageCut": 0,
    "dokonjo": 10000,
    "counter": 0,
    "addAction": 0,
    "addPoison": 0,
    "addDeepPoison": 0,
    "addSleep": 0,
    "addParalysis": 0,
    "conditionTurn": 0,
    "conditionCount": 0,
    "prizeHpUp": 0,
    "prizeBurstUp": 10000,
    "luxUp": 10000,
    "moneyUp": 10000,
    "raidUp": 10000
  },
  {
    "skillId": 1126,
    "imageId": 0,
    "thumbId": 5,
    "name": "SP Attack Gauge II",
    "description": "Uses only 2 special attack gauges. Has a 100% trigger rate.",
    "rank": 2,
    "maxLv": 15,
    "expType": 3,
    "sortId": 1126,
    "categoryEvolve": 29,
    "invokeType": 4,
    "invokeProb": 10000,
    "invokeProbPerLv": 0,
    "invokeShowTiming": 5,
    "attackUp": 10000,
    "burstCancel": 0,
    "damageCut": 20000,
    "dokonjo": 10000,
    "counter": 0,
    "addAction": 0,
    "addPoison": 0,
    "addDeepPoison": 0,
    "addSleep": 0,
    "addParalysis": 0,
    "conditionTurn": 0,
    "conditionCount": 0,
    "prizeHpUp": 0,
    "prizeBurstUp": 10000,
    "luxUp": 10000,
    "moneyUp": 10000,
    "raidUp": 10000
  }
]